MANIFEST.in
requirements.txt
setup.cfg
setup.py
hestia/__init__.py
hestia/_version.py
hestia/api.py
hestiaapi.egg-info/PKG-INFO
hestiaapi.egg-info/SOURCES.txt
hestiaapi.egg-info/dependency_links.txt
hestiaapi.egg-info/pbr.json
hestiaapi.egg-info/requires.txt
hestiaapi.egg-info/top_level.txt